jpy_sql_runner/__init__.py
jpy_sql_runner/__main__.py
jpy_sql_runner/cli.py
jpy_sql_runner/db_helper.py
jpy_sql_runner/sql_helper.py
jpy_sql_runner-0.1.4.dist-info/licenses/LICENSE
jpy_sql_runner-0.1.4.dist-info/METADATA
jpy_sql_runner-0.1.4.dist-info/WHEEL
jpy_sql_runner-0.1.4.dist-info/entry_points.txt
jpy_sql_runner-0.1.4.dist-info/top_level.txt
jpy_sql_runner-0.1.4.dist-info/RECORD
