Metadata-Version: 2.4
Name: jpy-sql-runner
Version: 0.1.4
Summary: A Python utility for executing SQL files against databases with support for multiple statements, comments, and pretty-printed results
Author: Jim Schilling
Maintainer: Jim Schilling
License-Expression: MIT
Project-URL: Homepage, https://github.com/jim-schilling/jpy-sql-runner
Project-URL: Documentation, https://github.com/jim-schilling/jpy-sql-runner#readme
Project-URL: Repository, https://github.com/jim-schilling/jpy-sql-runner.git
Project-URL: Issues, https://github.com/jim-schilling/jpy-sql-runner/issues
Project-URL: Changelog, https://github.com/jim-schilling/jpy-sql-runner/blob/main/README.md#changelog
Keywords: sql,database,cli,sqlalchemy,sqlite,postgresql,mysql
Classifier: Development Status :: 4 - Beta
Classifier: Intended Audience :: Developers
Classifier: Intended Audience :: System Administrators
Classifier: Operating System :: OS Independent
Classifier: Programming Language :: Python :: 3
Classifier: Programming Language :: Python :: 3.10
Classifier: Programming Language :: Python :: 3.11
Classifier: Programming Language :: Python :: 3.12
Classifier: Topic :: Database
Classifier: Topic :: Software Development :: Libraries :: Python Modules
Classifier: Topic :: Utilities
Classifier: Environment :: Console
Classifier: Typing :: Typed
Requires-Python: >=3.10
License-File: LICENSE
Requires-Dist: sqlalchemy>=2.0.37
Requires-Dist: sqlparse>=0.4.0
Requires-Dist: tabulate>=0.9.0
Provides-Extra: dev
Requires-Dist: pytest>=7.0.0; extra == "dev"
Requires-Dist: pytest-cov>=4.0.0; extra == "dev"
Requires-Dist: black>=23.0.0; extra == "dev"
Requires-Dist: flake8>=6.0.0; extra == "dev"
Requires-Dist: mypy>=1.0.0; extra == "dev"
Requires-Dist: pre-commit>=3.0.0; extra == "dev"
Provides-Extra: test
Requires-Dist: pytest>=7.0.0; extra == "test"
Requires-Dist: pytest-cov>=4.0.0; extra == "test"
Provides-Extra: lint
Requires-Dist: black>=23.0.0; extra == "lint"
Requires-Dist: flake8>=6.0.0; extra == "lint"
Requires-Dist: mypy>=1.0.0; extra == "lint"
Provides-Extra: docs
Requires-Dist: sphinx>=7.0.0; extra == "docs"
Requires-Dist: sphinx-rtd-theme>=1.0.0; extra == "docs"
Dynamic: license-file
